[{"code":"48110","value":"창원시"},{"code":"48160","value":"마산시"},{"code":"48170","value":"진주시"},{"code":"48190","value":"진해시"},{"code":"48220","value":"통영시"},{"code":"48240","value":"사천시"},{"code":"48250","value":"김해시"},{"code":"48270","value":"밀양시"},{"code":"48310","value":"거제시"},{"code":"48330","value":"양산시"},{"code":"48720","value":"의령군"},{"code":"48730","value":"함안군"},{"code":"48740","value":"창녕군"},{"code":"48820","value":"고성군"},{"code":"48840","value":"남해군"},{"code":"48850","value":"하동군"},{"code":"48860","value":"산청군"},{"code":"48870","value":"함양군"},{"code":"48880","value":"거창군"},{"code":"48890","value":"합천군"}]
